syncgitlab2msproject/__init__.py
syncgitlab2msproject/argparse_actions.py
syncgitlab2msproject/cli.py
syncgitlab2msproject/custom_types.py
syncgitlab2msproject/decorators.py
syncgitlab2msproject/exceptions.py
syncgitlab2msproject/funcions.py
syncgitlab2msproject/gitlab_issues.py
syncgitlab2msproject/helper_classes.py
syncgitlab2msproject/ms_project.py
syncgitlab2msproject/sync.py
SyncGitlab2MSProject-0.0.6.dist-info/AUTHORS.rst
SyncGitlab2MSProject-0.0.6.dist-info/LICENSE.txt
SyncGitlab2MSProject-0.0.6.dist-info/METADATA
SyncGitlab2MSProject-0.0.6.dist-info/WHEEL
SyncGitlab2MSProject-0.0.6.dist-info/entry_points.txt
SyncGitlab2MSProject-0.0.6.dist-info/top_level.txt
SyncGitlab2MSProject-0.0.6.dist-info/RECORD
