Metadata-Version: 2.1
Name: SyncGitlab2MSProject
Version: 0.0.6
Summary: Synchronized Gitlab Issues into Microsoft Project
Home-page: https://github.com/CarliJoy/SyncGitlab2MSProject
Author: Carli* Freudenberg
Author-email: carli.freudenberg@posteo.de
License: MIT
Project-URL: Documentation, https://syncgitlab2msproject.readthedocs.io/
Platform: any
Classifier: Development Status :: 4 - Beta
Classifier: Programming Language :: Python
Classifier: License :: OSI Approved :: MIT License
Classifier: Environment :: Win32 (MS Windows)
Classifier: Operating System :: Microsoft :: Windows :: Windows 10
Classifier: Programming Language :: Python :: 3.8
Classifier: Programming Language :: Python :: 3.9
Classifier: Topic :: Office/Business
Classifier: Typing :: Typed
Requires-Python: >=3.8
Requires-Dist: pywin32 (>=228)
Requires-Dist: python-gitlab (>=2.5.0)
Requires-Dist: python-dateutil (>=2.8.1)
Provides-Extra: build_doc
Requires-Dist: sphinx ; extra == 'build_doc'
Requires-Dist: recommonmark (>=0.6.0) ; extra == 'build_doc'
Requires-Dist: m2r2 ; extra == 'build_doc'
Provides-Extra: testing
Requires-Dist: pytest ; extra == 'testing'
Requires-Dist: pytest-cov ; extra == 'testing'
